masint/__init__.py
masint/api/__init__.py
masint/api/async_supermassive_intelligence.py
masint/api/supermassive_intelligence.py
masint/cli/__init__.py
masint/cli/ls.py
masint/cli/main.py
masint/cli/plot.py
masint/cli/squeue.py
masint/cli/view_logs.py
masint/engines/__init__.py
masint/engines/async_cray.py
masint/engines/cray/__init__.py
masint/engines/cray/submit_training_job.py
masint/util/__init__.py
masint/util/get_api_base.py
masint/util/make_api_url.py
cray_lm-0.5.1.dist-info/METADATA
cray_lm-0.5.1.dist-info/WHEEL
cray_lm-0.5.1.dist-info/entry_points.txt
cray_lm-0.5.1.dist-info/top_level.txt
cray_lm-0.5.1.dist-info/RECORD
