Metadata-Version: 2.2
Name: cray-lm
Version: 0.5.1
Summary: ScalarLM is an integrated LLM inference and training platform
Author-email: Greg Diamos <gregory.diamos@gmail.com>
Classifier: Programming Language :: Python :: 3
Classifier: License :: OSI Approved :: Apache Software License
Classifier: Operating System :: OS Independent
Requires-Python: >=3.7
Requires-Dist: aiohttp
Requires-Dist: aiofiles
Requires-Dist: jsonlines
Requires-Dist: matplotlib
